setup.cfg
setup.py
revlo/__init__.py
revlo/client.py
revlo.egg-info/PKG-INFO
revlo.egg-info/SOURCES.txt
revlo.egg-info/dependency_links.txt
revlo.egg-info/requires.txt
revlo.egg-info/top_level.txt