Metadata-Version: 1.1
Name: revlo
Version: 0.15.5
Summary: Revlo Python Client
Home-page: https://github.com/teamrevlo/revlo-python-client
Author: Scott Nguyen
Author-email: scott.q.nguyen@gmail.com
License: MIT
Download-URL: https://github.com/teamrevlo/revlo-python-client/tarball/0.15.5
Keywords: revlo-api,revlo,revloapi
Platform: UNKNOWN
Classifier: Development Status :: 5 - Production/Stable
Classifier: License :: OSI Approved :: MIT License
Classifier: Intended Audience :: Developers
Classifier: Topic :: Software Development
Classifier: Topic :: Software Development :: Libraries :: Python Modules
Classifier: Programming Language :: Python :: 2.7
Classifier: Programming Language :: Python :: 3.5
